sever.py
jacksun818_newmcp-0.1.0.dist-info/METADATA
jacksun818_newmcp-0.1.0.dist-info/WHEEL
jacksun818_newmcp-0.1.0.dist-info/entry_points.txt
jacksun818_newmcp-0.1.0.dist-info/top_level.txt
jacksun818_newmcp-0.1.0.dist-info/RECORD
