Metadata-Version: 2.4
Name: jacksun818-newmcp
Version: 0.1.0
Summary: Add your description here
Requires-Python: >=3.13
Requires-Dist: build>=1.3.0
Requires-Dist: fastmcp>=2.12.4
Requires-Dist: twine>=6.2.0
